{
  "version": "7",
  "dialect": "postgresql",
  "entries": [
    {
      "idx": 0,
      "version": "7",
      "when": 1728598022383,
      "tag": "0000_keen_devos",
      "breakpoints": true
    },
    {
      "idx": 1,
      "version": "7",
      "when": 1730305168442,
      "tag": "0001_jittery_ultimatum",
      "breakpoints": true
    },
    {
      "idx": 2,
      "version": "7",
      "when": 1730335635896,
      "tag": "0002_noisy_red_shift",
      "breakpoints": true
    },
    {
      "idx": 3,
      "version": "7",
      "when": 1730417479067,
      "tag": "0003_fair_outlaw_kid",
      "breakpoints": true
    }
  ]
}